check_proxy.py
config.py
core_functional.py
crazy_functional.py
main.py
multi_language.py
toolbox.py
crazy_functions/Conversation_To_File.py
crazy_functions/Image_Generate.py
crazy_functions/Image_Generate_Wrap.py
crazy_functions/Internet_GPT.py
crazy_functions/Internet_GPT_Wrap.py
crazy_functions/Latex_Function.py
crazy_functions/Latex_Function_Wrap.py
crazy_functions/Latex全文润色.py
crazy_functions/Latex全文翻译.py
crazy_functions/Markdown_Translate.py
crazy_functions/PDF_Translate.py
crazy_functions/PDF_Translate_Wrap.py
crazy_functions/Rag_Interface.py
crazy_functions/Social_Helper.py
crazy_functions/SourceCode_Analyse.py
crazy_functions/SourceCode_Comment.py
crazy_functions/__init__.py
crazy_functions/chatglm微调工具.py
crazy_functions/crazy_utils.py
crazy_functions/下载arxiv论文翻译摘要.py
crazy_functions/互动小游戏.py
crazy_functions/交互功能函数模板.py
crazy_functions/函数动态生成.py
crazy_functions/命令行助手.py
crazy_functions/多智能体.py
crazy_functions/总结word文档.py
crazy_functions/总结音视频.py
crazy_functions/批量总结PDF文档.py
crazy_functions/批量总结PDF文档pdfminer.py
crazy_functions/批量翻译PDF文档_NOUGAT.py
crazy_functions/数学动画生成manim.py
crazy_functions/理解PDF文档内容.py
crazy_functions/生成函数注释.py
crazy_functions/生成多种Mermaid图表.py
crazy_functions/知识库问答.py
crazy_functions/联网的ChatGPT.py
crazy_functions/联网的ChatGPT_bing版.py
crazy_functions/虚空终端.py
crazy_functions/解析JupyterNotebook.py
crazy_functions/询问多个大语言模型.py
crazy_functions/语音助手.py
crazy_functions/读文章写摘要.py
crazy_functions/谷歌检索小助手.py
crazy_functions/辅助功能.py
crazy_functions/高级功能函数模板.py
crazy_functions/agent_fns/auto_agent.py
crazy_functions/agent_fns/echo_agent.py
crazy_functions/agent_fns/general.py
crazy_functions/agent_fns/persistent.py
crazy_functions/agent_fns/pipe.py
crazy_functions/agent_fns/python_comment_agent.py
crazy_functions/agent_fns/python_comment_compare.html
crazy_functions/agent_fns/watchdog.py
crazy_functions/ast_fns/comment_remove.py
crazy_functions/diagram_fns/file_tree.py
crazy_functions/game_fns/game_ascii_art.py
chatgpt_academic-3.83.post1.dist-info/LICENSE
chatgpt_academic-3.83.post1.dist-info/METADATA
chatgpt_academic-3.83.post1.dist-info/WHEEL
chatgpt_academic-3.83.post1.dist-info/entry_points.txt
chatgpt_academic-3.83.post1.dist-info/top_level.txt
chatgpt_academic-3.83.post1.dist-info/RECORD
