Metadata-Version: 2.1
Name: chatgpt-academic
Version: 3.83.post1
Summary: ChatGPT Academic
Author-email: Wang Hailin <wanghailin@tongji.edu.cn>
Project-URL: Homepage, https://github.com/haiiliin/chatgpt-academic/
Classifier: Programming Language :: Python
Classifier: Programming Language :: Python :: 3
Classifier: License :: OSI Approved :: GNU General Public License v3 (GPLv3)
Requires-Python: >=3.8
License-File: LICENSE
Requires-Dist: fastapi
Requires-Dist: pypdf2 ==2.12.1
Requires-Dist: tiktoken >=0.3.3
Requires-Dist: requests[socks]
Requires-Dist: pydantic ==1.10.11
Requires-Dist: transformers >=4.27.1
Requires-Dist: scipdf-parser >=0.52
Requires-Dist: python-markdown-math
Requires-Dist: beautifulsoup4
Requires-Dist: prompt-toolkit
Requires-Dist: latex2mathml
Requires-Dist: python-docx
Requires-Dist: mdtex2html
Requires-Dist: anthropic
Requires-Dist: pyautogen
Requires-Dist: colorama
Requires-Dist: Markdown
Requires-Dist: pygments
Requires-Dist: pymupdf
Requires-Dist: openai
Requires-Dist: numpy
Requires-Dist: arxiv
Requires-Dist: rich
Requires-Dist: websocket-client
Requires-Dist: scipdf-parser >=0.3
Requires-Dist: aiofiles
Requires-Dist: aiohttp
Requires-Dist: altair >=4.2.0
Requires-Dist: ffmpy
Requires-Dist: gradio-client >=0.2.4
Requires-Dist: httpx
Requires-Dist: huggingface-hub >=0.13.0
Requires-Dist: jinja2
Requires-Dist: markdown-it-py[linkify] >=2.0.0
Requires-Dist: markupsafe
Requires-Dist: matplotlib
Requires-Dist: mdit-py-plugins <=0.3.3
Requires-Dist: orjson
Requires-Dist: pandas
Requires-Dist: pillow
Requires-Dist: pydantic
Requires-Dist: pydub
Requires-Dist: pygments >=2.12.0
Requires-Dist: python-multipart
Requires-Dist: pyyaml
Requires-Dist: requests
Requires-Dist: semantic-version
Requires-Dist: typing-extensions
Requires-Dist: uvicorn >=0.14.0
Requires-Dist: websockets >=10.0
Provides-Extra: all
Requires-Dist: chatgpt-academic[chatglm,chatglm_onnx,dev,jittorllms,moss,newbing,qwen,slackclaude] ; extra == 'all'
Provides-Extra: chatglm
Requires-Dist: protobuf ; extra == 'chatglm'
Requires-Dist: cpm-kernels ; extra == 'chatglm'
Requires-Dist: torch >=1.10 ; extra == 'chatglm'
Requires-Dist: mdtex2html ; extra == 'chatglm'
Requires-Dist: sentencepiece ; extra == 'chatglm'
Provides-Extra: chatglm_onnx
Requires-Dist: protobuf ; extra == 'chatglm_onnx'
Requires-Dist: cpm-kernels ; extra == 'chatglm_onnx'
Requires-Dist: torch >=1.10 ; extra == 'chatglm_onnx'
Requires-Dist: mdtex2html ; extra == 'chatglm_onnx'
Requires-Dist: sentencepiece ; extra == 'chatglm_onnx'
Requires-Dist: numpy ; extra == 'chatglm_onnx'
Requires-Dist: onnxruntime ; extra == 'chatglm_onnx'
Provides-Extra: dev
Requires-Dist: pyinstaller >=6.1.0 ; extra == 'dev'
Provides-Extra: jittorllms
Requires-Dist: jittor >=1.3.7.9 ; extra == 'jittorllms'
Requires-Dist: jtorch >=0.1.3 ; extra == 'jittorllms'
Requires-Dist: torch ; extra == 'jittorllms'
Requires-Dist: torchvision ; extra == 'jittorllms'
Requires-Dist: pandas ; extra == 'jittorllms'
Requires-Dist: jieba ; extra == 'jittorllms'
Provides-Extra: moss
Requires-Dist: torch ; extra == 'moss'
Requires-Dist: sentencepiece ; extra == 'moss'
Requires-Dist: datasets ; extra == 'moss'
Requires-Dist: accelerate ; extra == 'moss'
Requires-Dist: matplotlib ; extra == 'moss'
Requires-Dist: huggingface-hub ; extra == 'moss'
Requires-Dist: triton ; extra == 'moss'
Requires-Dist: streamlit ; extra == 'moss'
Provides-Extra: newbing
Requires-Dist: BingImageCreator ; extra == 'newbing'
Requires-Dist: certifi ; extra == 'newbing'
Requires-Dist: httpx ; extra == 'newbing'
Requires-Dist: prompt-toolkit ; extra == 'newbing'
Requires-Dist: requests ; extra == 'newbing'
Requires-Dist: rich ; extra == 'newbing'
Requires-Dist: websockets ; extra == 'newbing'
Requires-Dist: httpx[socks] ; extra == 'newbing'
Provides-Extra: qwen
Requires-Dist: dashscope ; extra == 'qwen'
Requires-Dist: modelscope ; extra == 'qwen'
Requires-Dist: transformers-stream-generator ; extra == 'qwen'
Requires-Dist: auto-gptq ; extra == 'qwen'
Requires-Dist: optimum ; extra == 'qwen'
Requires-Dist: urllib3 <2 ; extra == 'qwen'
Provides-Extra: slackclaude
Requires-Dist: slack-sdk ==3.21.3 ; extra == 'slackclaude'
